napalm_servertech_pro2/__init__.py
napalm_servertech_pro2/constants.py
napalm_servertech_pro2/pro2.py
napalm_servertech_pro2/utils.py
napalm_servertech_pro2-0.1.5.dist-info/LICENSE
napalm_servertech_pro2-0.1.5.dist-info/METADATA
napalm_servertech_pro2-0.1.5.dist-info/WHEEL
napalm_servertech_pro2-0.1.5.dist-info/top_level.txt
napalm_servertech_pro2-0.1.5.dist-info/RECORD
