Metadata-Version: 2.1
Name: napalm-servertech-pro2
Version: 0.1.5
Summary: NAPALM driver for ServerTech PRO2 PDUs
Home-page: https://github.com/napalm-automation-community/napalm-servertech-pro2
Author: Antoine Meillet
Author-email: antoine.meillet@gmail.com
License: Apache 2.0
Classifier: Topic :: Utilities
Classifier: Programming Language :: Python
Classifier: Programming Language :: Python :: 3
Classifier: Programming Language :: Python :: 3.8
Classifier: Programming Language :: Python :: 3.9
Classifier: Programming Language :: Python :: 3.10
Classifier: Programming Language :: Python :: 3.11
Classifier: Programming Language :: Python :: 3.12
Classifier: Operating System :: POSIX :: Linux
Classifier: Operating System :: MacOS
License-File: LICENSE
Requires-Dist: napalm >=4.1.0
Requires-Dist: netaddr >=0.10.1
Requires-Dist: requests >=2.31.0
